markov_matrix/__init__.py
markov_matrix/matrix_chain.py
markov_matrix-0.1.2.dist-info/LICENSE
markov_matrix-0.1.2.dist-info/WHEEL
markov_matrix-0.1.2.dist-info/METADATA
markov_matrix-0.1.2.dist-info/RECORD
