Metadata-Version: 2.1
Name: markov-matrix
Version: 0.1.2
Summary: A package for generating markov matrices
License: MIT
Author: peder2911
Author-email: pglandsverk@gmail.com
Requires-Python: >=3.8,<=3.10
Classifier: License :: OSI Approved :: MIT License
Classifier: Programming Language :: Python :: 3
Classifier: Programming Language :: Python :: 3.10
Classifier: Programming Language :: Python :: 3.8
Classifier: Programming Language :: Python :: 3.9
Requires-Dist: numpy (>=1.21.2,<2.0.0)
